robots_controller/__init__.py
robots_controller/__test.py
robots_controller/common/Logger.py
robots_controller/common/__init__.py
robots_controller/common/error.py
robots_controller/connectors/ForisAPIConnector.py
robots_controller/connectors/ServiceProxyConnector.py
robots_controller/connectors/SiebelAPIConnector.py
robots_controller/connectors/__init__.py
robots_controller/dal/dcs_getInqueryByNumber.py
robots_controller/helpers/json.py
robots_controller-1.0.12.dist-info/AUTHORS
robots_controller-1.0.12.dist-info/LICENSE
robots_controller-1.0.12.dist-info/METADATA
robots_controller-1.0.12.dist-info/WHEEL
robots_controller-1.0.12.dist-info/entry_points.txt
robots_controller-1.0.12.dist-info/top_level.txt
robots_controller-1.0.12.dist-info/RECORD
