Metadata-Version: 2.1
Name: robots-controller
Version: 1.0.12
Summary: Smart robots controller 1
Home-page: https://gitlab.com/SamSafonov/robots_controller
Author: Semyon Safonov
Author-email: samsaf@gmail.com
License: BSD 1
Platform: UNKNOWN
